autoflatten/__init__.py
autoflatten/_version.py
autoflatten/cli.py
autoflatten/config.py
autoflatten/core.py
autoflatten/freesurfer.py
autoflatten/logging.py
autoflatten/template.py
autoflatten/utils.py
autoflatten/viz.py
autoflatten/backends/__init__.py
autoflatten/backends/base.py
autoflatten/backends/freesurfer.py
autoflatten/backends/pyflatten.py
autoflatten/default_templates/fsaverage_cuts_template.json
autoflatten/flatten/__init__.py
autoflatten/flatten/algorithm.py
autoflatten/flatten/config.py
autoflatten/flatten/distance.py
autoflatten/flatten/energy.py
autoflatten/flatten/threading.py
autoflatten/tests/__init__.py
autoflatten/tests/conftest.py
autoflatten/tests/test_backends.py
autoflatten/tests/test_cli.py
autoflatten/tests/test_config.py
autoflatten/tests/test_core.py
autoflatten/tests/test_flatten.py
autoflatten/tests/test_freesurfer.py
autoflatten/tests/test_logging.py
autoflatten/tests/test_template.py
autoflatten/tests/test_threading.py
autoflatten/tests/test_utils.py
autoflatten/tests/test_version.py
autoflatten/tests/test_viz.py
autoflatten-1.0.6.dist-info/licenses/LICENSE
autoflatten-1.0.6.dist-info/METADATA
autoflatten-1.0.6.dist-info/WHEEL
autoflatten-1.0.6.dist-info/entry_points.txt
autoflatten-1.0.6.dist-info/top_level.txt
autoflatten-1.0.6.dist-info/RECORD
