Metadata-Version: 2.4
Name: autoflatten
Version: 1.0.6
Summary: Automatically create cortical flatmaps from FreeSurfer surfaces
Author-email: Matteo Visconti di Oleggio Castello <mvdoc@berkeley.edu>
License-Expression: BSD-2-Clause
Project-URL: Repository, https://github.com/gallantlab/autoflatten
Classifier: Development Status :: 5 - Production/Stable
Classifier: Intended Audience :: Science/Research
Classifier: Operating System :: OS Independent
Classifier: Programming Language :: Python :: 3
Classifier: Programming Language :: Python :: 3.10
Classifier: Programming Language :: Python :: 3.11
Classifier: Programming Language :: Python :: 3.12
Classifier: Programming Language :: Python :: 3.13
Classifier: Topic :: Scientific/Engineering
Requires-Python: >=3.10
License-File: LICENSE
Requires-Dist: numpy
Requires-Dist: networkx
Requires-Dist: scikit-learn
Requires-Dist: packaging
Requires-Dist: jax>=0.4.0
Requires-Dist: libigl>=2.5.0
Requires-Dist: nibabel>=5.0.0
Requires-Dist: numba>=0.58.0
Requires-Dist: scipy>=1.10.0
Requires-Dist: tqdm>=4.65.0
Requires-Dist: matplotlib>=3.7.0
Provides-Extra: test
Requires-Dist: pytest; extra == "test"
Requires-Dist: pytest-cov; extra == "test"
Requires-Dist: codecov; extra == "test"
Provides-Extra: docs
Requires-Dist: mkdocs-material; extra == "docs"
Dynamic: license-file
